dle/__init__.py
dle/__main__.py
dle/__version__.py
dle-0.1.2.dist-info/LICENSE.txt
dle-0.1.2.dist-info/METADATA
dle-0.1.2.dist-info/WHEEL
dle-0.1.2.dist-info/entry_points.txt
dle-0.1.2.dist-info/top_level.txt
dle-0.1.2.dist-info/RECORD
